hunabku_openscienti/__init__.py
hunabku_openscienti/_version.py
hunabku_openscienti/endpoints/OpenScienti.py
Hunabku_openscienti-0.0.3.dist-info/METADATA
Hunabku_openscienti-0.0.3.dist-info/WHEEL
Hunabku_openscienti-0.0.3.dist-info/top_level.txt
Hunabku_openscienti-0.0.3.dist-info/RECORD
